{
  "minVersion": "0.8",
  "package": "mod.adrenix.nostalgic.mixin.client",
  "plugin": "mod.adrenix.nostalgic.mixin.MixinPlugin",
  "compatibilityLevel": "JAVA_17",
  "priority": 1001,
  "client": [
    "gui.AbstractWidgetMixin",
    "gui.BackupConfirmScreenMixin",
    "gui.ChatComponentMixin",
    "gui.ChatScreenMixin",
    "gui.GuiMixin",
    "gui.LoadingOverlayMixin",
    "gui.ScreenMixin",
    "gui.WorldListEntryMixin",
    "renderer.BlockEntityRenderDispatcherMixin",
    "renderer.ExperienceOrbRendererMixin",
    "renderer.FogRendererMixin",
    "renderer.GameRendererMixin",
    "renderer.GhastRendererMixin",
    "renderer.ItemEntityRendererMixin",
    "renderer.ItemFrameRendererMixin",
    "renderer.ItemInHandRendererMixin",
    "renderer.ItemModelGeneratorMixin",
    "renderer.ItemRendererMixin",
    "renderer.LevelRendererMixin",
    "renderer.LightTextureMixin",
    "renderer.ThrownItemRendererMixin",
    "model.AbstractZombieModelMixin",
    "model.AnimationUtilsMixin",
    "model.SkeletonModelMixin",
    "world.BiomeMixin",
    "world.ClientLevelMixin",
    "world.DimensionTypeMixin",
    "CameraMixin",
    "MinecraftMixin",
    "ModelBakeryMixin",
    "ParticleEngineMixin"
  ]
}